tremendous/__init__.py
tremendous/api_client.py
tremendous/api_response.py
tremendous/configuration.py
tremendous/exceptions.py
tremendous/py.typed
tremendous/rest.py
tremendous/version.py
tremendous/api/__init__.py
tremendous/api/tremendous_api.py
tremendous/models/__init__.py
tremendous/models/allow_email.py
tremendous/models/allow_email1.py
tremendous/models/allow_ip.py
tremendous/models/allow_ip1.py
tremendous/models/balance_transaction.py
tremendous/models/balance_transaction_order.py
tremendous/models/balance_transaction_order_payment.py
tremendous/models/base_order_for_create.py
tremendous/models/campaign.py
tremendous/models/campaign_base.py
tremendous/models/channel.py
tremendous/models/connected_organization.py
tremendous/models/connected_organization_member.py
tremendous/models/connected_organization_member_member.py
tremendous/models/connected_organization_member_session.py
tremendous/models/connected_organization_organization.py
tremendous/models/create_api_key200_response.py
tremendous/models/create_campaign200_response.py
tremendous/models/create_campaign201_response.py
tremendous/models/create_campaign_request.py
tremendous/models/create_connected_organization200_response.py
tremendous/models/create_connected_organization_member200_response.py
tremendous/models/create_connected_organization_member_request.py
tremendous/models/create_connected_organization_member_session200_response.py
tremendous/models/create_connected_organization_member_session200_response_connected_organization_member_session.py
tremendous/models/create_connected_organization_member_session_request.py
tremendous/models/create_connected_organization_request.py
tremendous/models/create_invoice200_response.py
tremendous/models/create_invoice_request.py
tremendous/models/create_member.py
tremendous/models/create_member200_response.py
tremendous/models/create_member_request.py
tremendous/models/create_order200_response.py
tremendous/models/create_order200_response_order.py
tremendous_python-5.4.0.dist-info/licenses/LICENSE
tremendous_python-5.4.0.dist-info/METADATA
tremendous_python-5.4.0.dist-info/WHEEL
tremendous_python-5.4.0.dist-info/top_level.txt
tremendous_python-5.4.0.dist-info/RECORD
