Metadata-Version: 2.4
Name: tremendous-python
Version: 5.4.0
Summary: Python API client for Tremendous
Home-page: https://github.com/tremendous-rewards/tremendous-python
Author: Tremendous
Author-email: developers@tremendous.com
Keywords: Api,Gift cards,Rewards,Incentives,Tremendous
License-File: LICENSE
Requires-Dist: urllib3<3.0.0,>=2.1.0
Requires-Dist: python-dateutil
Requires-Dist: pydantic>=2
Requires-Dist: typing-extensions>=4.7.1
Dynamic: author
Dynamic: author-email
Dynamic: description
Dynamic: home-page
Dynamic: keywords
Dynamic: license-file
Dynamic: requires-dist
Dynamic: summary
